lib_fetcher_image/__init__.py
lib_fetcher_image/fetcher.py
lib_fetcher_image-2.3.4.dist-info/METADATA
lib_fetcher_image-2.3.4.dist-info/WHEEL
lib_fetcher_image-2.3.4.dist-info/top_level.txt
lib_fetcher_image-2.3.4.dist-info/RECORD
