Metadata-Version: 2.4
Name: lib_fetcher_image
Version: 2.3.4
Summary: Library for search images
Home-page: https://github.com/YuranIgnatenko/lib_fetcher_image
Author: Yurij
Author-email: yuran.ignatenko@yandex.ru
Requires-Dist: requests
Requires-Dist: beautifulsoup4
Requires-Dist: fake_useragent
Requires-Dist: Pillow
Dynamic: author
Dynamic: author-email
Dynamic: description
Dynamic: description-content-type
Dynamic: home-page
Dynamic: requires-dist
Dynamic: summary
